pyswtools/__init__.py
pyswtools/auto_exporter/__init__.py
pyswtools/auto_exporter/main.py
pyswtools/clean/__init__.py
pyswtools/clean/main.py
pyswtools/config.py
pyswtools/copy_full_assembly/__init__.py
pyswtools/copy_full_assembly/main.py
pyswtools/helper_sw.py
pyswtools/main.py
pyswtools/properties/__init__.py
pyswtools/properties/main.py
pyswtools/ready_dxf/__init__.py
pyswtools/ready_dxf/dxf_utilities.py
pyswtools/ready_dxf/file_utilities.py
pyswtools/ready_dxf/main.py
pyswtools/stat/__init__.py
pyswtools/stat/definitions.py
pyswtools/stat/main.py
pyswtools/utils.py
pyswtools-0.8.1.dist-info/LICENSE
pyswtools-0.8.1.dist-info/METADATA
pyswtools-0.8.1.dist-info/WHEEL
pyswtools-0.8.1.dist-info/entry_points.txt
pyswtools-0.8.1.dist-info/RECORD
