Metadata-Version: 2.1
Name: pyswtools
Version: 0.8.1
Summary: Set of tools to improve Solidworks usage
Home-page: https://github.com/ldevillez/pySwTools
License: GNU General Public License
Author: ldevillez
Author-email: louis.devillez@gmail.com
Requires-Python: >=3.10,<4.0
Classifier: License :: Other/Proprietary License
Classifier: Programming Language :: Python :: 3
Classifier: Programming Language :: Python :: 3.10
Classifier: Programming Language :: Python :: 3.11
Classifier: Programming Language :: Python :: 3.12
Requires-Dist: appdirs (>=1.4.4,<2.0.0)
Requires-Dist: click (>=8.1.3,<9.0.0)
Requires-Dist: ezdxf (>=1.0.3,<2.0.0)
Requires-Dist: numpy-stl (>=3.0.1,<4.0.0)
Requires-Dist: pydantic (>=1.10.7,<2.0.0)
Requires-Dist: pywin32 (>=306,<307) ; sys_platform == "win32"
Requires-Dist: rtoml (>=0.9.0,<0.10.0)
Project-URL: Repository, https://github.com/ldevillez/pySwTools
